{
  "unversionedId": "webrtc/nanostream_webrtc_speech_music",
  "id": "webrtc/nanostream_webrtc_speech_music",
  "title": "Speech / Music Streaming",
  "description": "Since Webcaster version 5.8.0 additional audio preprocessing options are available.",
  "source": "@site/docs/webrtc/nanostream_webrtc_speech_music.md",
  "sourceDirName": "webrtc",
  "slug": "/webrtc/nanostream_webrtc_speech_music",
  "permalink": "/docs/webrtc/nanostream_webrtc_speech_music",
  "draft": false,
  "tags": [],
  "version": "current",
  "lastUpdatedAt": 1539502055,
  "formattedLastUpdatedAt": "Oct 14, 2018",
  "frontMatter": {
    "id": "nanostream_webrtc_speech_music",
    "title": "Speech / Music Streaming",
    "sidebar_label": "Speech / Music Streaming"
  },
  "sidebar": "nanoStream Webcaster",
  "previous": {
    "title": "Audio- / Video-Only",
    "permalink": "/docs/webrtc/nanostream_webrtc_audio_video_only"
  },
  "next": {
    "title": "External Streams / Mixing",
    "permalink": "/docs/webrtc/nanostream_webrtc_set_mediastream"
  }
}